{
  "projects": [
    {
      "id": 1,
      "title": "kaizen",
      "date": "2023",
      "client": "Michael Badiako",
      "location": "Ghana",
      "live": "",
      "description": "Rebranded the company from iamadinkra which was more of a personal brand to kaizen av project, worked on designing the logo, and other brand assets including the brand manual, t-shirts, documents, and business cards, with extensive research aligning to the brands vision and appearance. \n\n Worked on Redesigning and developing the new look for kaizen av projects, I created user flows to help visualize how users will interact with the website , designed all the pages on Figma with interesting UI an interactive prototyping, After I received approval from the client, I began the development for the website using the latest technologies add on features that will make kaizen av projects stand out from it competitors.",
      "status": "notonline",
      "imageUrl": "/images/kaizen.jpg",
      "category": [
        "React",
        "Interactive",
        "React-router",
        "GSAP",
        "Sass"
      ],
      "video":"https://res.cloudinary.com/base-data/video/upload/ac_none,q_40/v1693874949/images/kaizen/video.mp4",
      "images": [
        "https://res.cloudinary.com/base-data/video/upload/ac_none/v1693359206/images/kaizen/kaizen-design-vid.gif",
        "/images/kaizen/02.jpg",
        "/images/kaizen/03.jpg",
        "/images/kaizen/04.jpg",
        "/images/kaizen/gif.gif",
        "/images/kaizen/last-long.jpg"
      ]
    },
    {
      "id": 2,
      "title": "Desoc Website",
      "date": "2020",
      "client": "Unkown",
      "location": "Ghana",
      "live": "https://desoc-so.netlify.app/",
      "description": "A landing page for the Department of Graphic Design at the University of Education, Winneba",
      "status": "online",
      "imageUrl": "/images/desoc.jpg",
      "category": ["Website", "Web design", "GSAP"],
      "images": [
        "/images/desoc/00.jpg",
        "/images/desoc/01.jpg",
        "/images/desoc/02.jpg",
        "/images/desoc/03.jpg",
        "/images/desoc/04.jpg",
        "/images/desoc/05.jpg"
      ]
    },
    {
      "id": 3,
      "title": "Leava",
      "date": "2023",
      "client": "Leava",
      "location": "Ghana",
      "live": "https://leava.framer.website/",
      "description": "A simple landing page built in framer",
      "status": "online",
      "imageUrl": "/images/leava.jpg",
      "category": ["Website", "Framer", "Web design"],
      "images": [
        "/images/leava/00.jpg",
        "/images/leava/gif.gif",
        "/images/leava/long.jpg"
      ]
    }
  ]
}
